setup.py
nsmysql/__init__.py
nsmysql/load_ns_mysql.py
nsmysql.egg-info/PKG-INFO
nsmysql.egg-info/SOURCES.txt
nsmysql.egg-info/dependency_links.txt
nsmysql.egg-info/not-zip-safe
nsmysql.egg-info/requires.txt
nsmysql.egg-info/top_level.txt