Metadata-Version: 1.0
Name: nsmysql
Version: 0.13
Summary: Data exchange from net suite data to MySQL database, fixed encoding issue
Home-page: https://github.com/ghao2/nsmysql
Author: Guoxuan Hao
Author-email: haoguoxuan@gmail.com
License: MIT
Platform: UNKNOWN
